MANIFEST.in
README.md
setup.py
PyXbSymbolDatabase.egg-info/PKG-INFO
PyXbSymbolDatabase.egg-info/SOURCES.txt
PyXbSymbolDatabase.egg-info/dependency_links.txt
PyXbSymbolDatabase.egg-info/top_level.txt
XbSymbolDatabase/__init__.py
XbSymbolDatabase/__main__.py
XbSymbolDatabase/XbSymbolDatabase/.gitattributes
XbSymbolDatabase/XbSymbolDatabase/.gitconfig
XbSymbolDatabase/XbSymbolDatabase/.gitignore
XbSymbolDatabase/XbSymbolDatabase/CMakeLists.txt
XbSymbolDatabase/XbSymbolDatabase/LICENSE
XbSymbolDatabase/XbSymbolDatabase/OOVPA.h
XbSymbolDatabase/XbSymbolDatabase/README.md
XbSymbolDatabase/XbSymbolDatabase/XbSymbolDatabase.c
XbSymbolDatabase/XbSymbolDatabase/XbSymbolDatabase.h
XbSymbolDatabase/XbSymbolDatabase/Xbe.h
XbSymbolDatabase/XbSymbolDatabase/.git/COMMIT_EDITMSG
XbSymbolDatabase/XbSymbolDatabase/.git/HEAD
XbSymbolDatabase/XbSymbolDatabase/.git/ORIG_HEAD
XbSymbolDatabase/XbSymbolDatabase/.git/config
XbSymbolDatabase/XbSymbolDatabase/.git/description
XbSymbolDatabase/XbSymbolDatabase/.git/index
XbSymbolDatabase/XbSymbolDatabase/.git/packed-refs
XbSymbolDatabase/XbSymbolDatabase/.git/hooks/applypatch-msg.sample
XbSymbolDatabase/XbSymbolDatabase/.git/hooks/commit-msg.sample
XbSymbolDatabase/XbSymbolDatabase/.git/hooks/fsmonitor-watchman.sample
XbSymbolDatabase/XbSymbolDatabase/.git/hooks/post-update.sample
XbSymbolDatabase/XbSymbolDatabase/.git/hooks/pre-applypatch.sample
XbSymbolDatabase/XbSymbolDatabase/.git/hooks/pre-commit.sample
XbSymbolDatabase/XbSymbolDatabase/.git/hooks/pre-push.sample
XbSymbolDatabase/XbSymbolDatabase/.git/hooks/pre-rebase.sample
XbSymbolDatabase/XbSymbolDatabase/.git/hooks/pre-receive.sample
XbSymbolDatabase/XbSymbolDatabase/.git/hooks/prepare-commit-msg.sample
XbSymbolDatabase/XbSymbolDatabase/.git/hooks/update.sample
XbSymbolDatabase/XbSymbolDatabase/.git/info/exclude
XbSymbolDatabase/XbSymbolDatabase/.git/logs/HEAD
XbSymbolDatabase/XbSymbolDatabase/.git/logs/refs/heads/cli-tool
XbSymbolDatabase/XbSymbolDatabase/.git/logs/refs/heads/fix
XbSymbolDatabase/XbSymbolDatabase/.git/logs/refs/heads/master
XbSymbolDatabase/XbSymbolDatabase/.git/logs/refs/remotes/origin/HEAD
