Metadata-Version: 2.1
Name: PyXbSymbolDatabase
Version: 0.0.1
Summary: Python bindings to XbSymbolDatabase
Home-page: https://github.com/mborgerson/PyXbSymbolDatabase
Author: Matt Borgerson
Author-email: contact@mborgerson.com
License: GPL
Platform: UNKNOWN
